.gitignore
LICENSE.txt
README.md
requirements-dev.txt
requirements.txt
setup.cfg
setup.py
.github/workflows/build-and-test.yml
.github/workflows/push-to-pip.yml
fastforward/__init__.py
fastforward/config.py
fastforward/model.py
fastforward/model_for_cross_encoding.py
fastforward/model_for_encoding.py
fastforward/model_for_generic.py
fastforward/model_for_question_answering.py
fastforward/model_for_sequence_classification.py
fastforward/model_for_sequence_similarity.py
fastforward/model_for_summarization.py
fastforward/model_for_translation.py
fastforward/__test__/lo_951_test.py
fastforward/__test__/model_for_classification_test.py
fastforward/__test__/model_for_cross_encoding_test.py
fastforward/__test__/model_for_encoding_test.py
fastforward/__test__/model_for_question_answering_test.py
fastforward/__test__/model_for_sequence_similarity_test.py
fastforward/__test__/model_for_summarization_test.py
fastforward/__test__/dummy/config.json
fastforward/__test__/dummy/info.json
fastforward/__test__/dummy/model.onnx
fastforward/__test__/dummy/tokenizer.json
fastforward/__test__/metric/benchmark.py
fastforward/__test__/metric/profiler.py
fastforward/engine/abstract_engine.py
fastforward/engine/onnx_engine.py
fastforward/engine/listener/onnx_listener.py
fastforward/generation/__init__.py
fastforward/generation/generation_config.py
fastforward/generation/generation_mixin.py
fastforward/generation/generator/__init__.py
fastforward/generation/generator/abstract_generator.py
fastforward/generation/generator/bart_generator.py
fastforward/generation/generator/marian_generator.py
fastforward/generation/generator/pegasus_generator.py
fastforward/generation/generator/t5_generator.py
fastforward/generation/strategy/__init__.py
fastforward/generation/strategy/abstract_strategy.py
fastforward/generation/strategy/beam_gen_mode_strategy.py
fastforward/generation/strategy/greedy_gen_mode_strategy.py
fastforward/generation/strategy/_logits_processor/__init__.py
x_and_y.fastforward_cpu.egg-info/PKG-INFO
x_and_y.fastforward_cpu.egg-info/SOURCES.txt
x_and_y.fastforward_cpu.egg-info/dependency_links.txt
x_and_y.fastforward_cpu.egg-info/requires.txt
x_and_y.fastforward_cpu.egg-info/top_level.txt