Metadata-Version: 2.1
Name: x-and-y.fastforward-cpu
Version: 0.1.8
Summary: Fastforward is an inference engine for efficient AI models.
Home-page: https://github.com/c7nw3r/fastforward
Author: x-and-y
Author-email: christian.weber@leftshift.one
License: Apache Software License
Download-URL: https://github.com/c7nw3r/fastforward/archive/refs/tags/v0.1.8.tar.gz
Keywords: onnx-engine,machine-learning,artificial-intelligence
Platform: UNKNOWN
Classifier: Development Status :: 4 - Beta
Classifier: Intended Audience :: Developers
Classifier: Topic :: Scientific/Engineering :: Artificial Intelligence
Classifier: License :: OSI Approved :: Apache Software License
Classifier: Programming Language :: Python :: 3
Classifier: Programming Language :: Python :: 3.4
Classifier: Programming Language :: Python :: 3.5
Classifier: Programming Language :: Python :: 3.6
